song_metadata_client/__init__.py
song_metadata_client/classes/__init__.py
song_metadata_client/classes/clients/__init__.py
song_metadata_client/classes/clients/spotify_metadata_client.py
song_metadata_client/classes/clients/ytmusic_metadata_client.py
song_metadata_client/classes/config/__init__.py
song_metadata_client/classes/config/spotify_options.py
song_metadata_client/classes/handlers/__init__.py
song_metadata_client/classes/handlers/spotify_playlist_handler.py
song_metadata_client/classes/handlers/spotify_search_handler.py
song_metadata_client/classes/handlers/spotify_track_handler.py
song_metadata_client/classes/handlers/ytmusic_playlist_handler.py
song_metadata_client/classes/handlers/ytmusic_search_handler.py
song_metadata_client/classes/handlers/ytmusic_track_handler.py
song_metadata_client/classes/playlist_metadata.py
song_metadata_client/classes/song_metadata.py
song_metadata_client/di/__init__.py
song_metadata_client/di/dependency_injector.py
song_metadata_client/errors/__init__.py
song_metadata_client/errors/metadata_client_error.py
song_metadata_client/interfaces/__init__.py
song_metadata_client/interfaces/base_metadata_client.py
song_metadata_client/main.py
song_metadata_client/py.typed
song_metadata_client-0.0.2.dist-info/LICENSE
song_metadata_client-0.0.2.dist-info/METADATA
song_metadata_client-0.0.2.dist-info/WHEEL
song_metadata_client-0.0.2.dist-info/RECORD
