Metadata-Version: 2.1
Name: song-metadata-client
Version: 0.0.2
Summary: A generic client to fetch metadata for any song
Home-page: https://github.com/Billuc/song-metadata-client
License: MIT
Keywords: metadata,python,song metadata,spotify,youtube,youtube music,music,song
Author: Billuc
Author-email: billuc@hotmail.fr
Requires-Python: >=3.9,<4.0
Classifier: Intended Audience :: End Users/Desktop
Classifier: License :: OSI Approved :: MIT License
Classifier: Programming Language :: Python
Classifier: Programming Language :: Python :: 3
Classifier: Programming Language :: Python :: 3.9
Classifier: Programming Language :: Python :: 3.10
Classifier: Programming Language :: Python :: 3.11
Classifier: Topic :: Multimedia
Classifier: Topic :: Multimedia :: Sound/Audio
Classifier: Topic :: Utilities
Requires-Dist: python-slugify (>=8.0.1,<9.0.0)
Requires-Dist: rapidfuzz (>=3.1.1,<4.0.0)
Requires-Dist: spotipy (>=2.23.0,<3.0.0)
Requires-Dist: taipan-di (==0.0.7)
Requires-Dist: ytmusicapi (>=1.0.2,<2.0.0)
Project-URL: Documentation, https://github.com/Billuc/song-metadata-client
Project-URL: Repository, https://github.com/Billuc/song-metadata-client
